pywolt/__init__.py
pywolt/api.py
pywolt/data_structures.py
pywolt/py.typed
pywolt-0.1.0.dist-info/LICENSE.txt
pywolt-0.1.0.dist-info/METADATA
pywolt-0.1.0.dist-info/WHEEL
pywolt-0.1.0.dist-info/top_level.txt
pywolt-0.1.0.dist-info/RECORD
