Metadata-Version: 2.1
Name: pywolt
Version: 0.1.0
Summary: PyWolt is a Python library that provides an open API for interacting with the popular food delivery application Wolt.
Author-email: Ilya Feldman <ilyafeldm@gmail.com>
Requires-Python: >=3.9
License-File: LICENSE.txt
Requires-Dist: httpx[http2] >=0.25.0
Requires-Dist: pycountry >=24.6.1
Requires-Dist: pydantic >=2.9.2
Requires-Dist: pydantic-extra-types >=2.9.0
Requires-Dist: pydantic-geojson >=0.1.1
